CHANGELOG.md
CONTRIBUTING.md
LICENSE.md
docs/CHANGELOG.md
docs/CONTRIBUTING.md
docs/LICENSE.md
docs/README.md
docs/conf.py
docs/index.rst
docs/selenium_probes.helpers.rst
docs/selenium_probes.probes.rst
docs/selenium_probes.rst
selenium_probes/__init__.py
selenium_probes/helpers/__init__.py
selenium_probes/helpers/browser.py
selenium_probes/helpers/vault.py
selenium_probes/probes/__init__.py
selenium_probes/probes/probe_abstract.py
selenium_probes/probes/probe_form.py
selenium_probes/probes/probe_page.py
tests/__init__.py
tests/conftest.py
tests/test_helpers_browser.py
tests/test_helpers_vault.py
tests/test_probes.py
tox.ini
selenium_probes-0.1.0.dist-info/LICENSE.md
selenium_probes-0.1.0.dist-info/WHEEL
selenium_probes-0.1.0.dist-info/METADATA
selenium_probes-0.1.0.dist-info/RECORD
