Metadata-Version: 2.1
Name: selenium-probes
Version: 0.1.0
Summary: A framework for building Selenium-based probes.
Home-page: https://github.com/undp/SeleniumProbes
License: MIT
Keywords: development,monitoring,selenium
Author: Oleksiy Kuzmenko
Author-email: oleksiy.kuzmenko@undp.org
Requires-Python: >=3.6,<4.0
Classifier: Development Status :: 4 - Beta
Classifier: Intended Audience :: Developers
Classifier: License :: OSI Approved :: MIT License
Classifier: Natural Language :: English
Classifier: Operating System :: POSIX :: Linux
Classifier: Programming Language :: Python :: 3
Classifier: Programming Language :: Python :: 3.6
Classifier: Programming Language :: Python :: 3.7
Classifier: Topic :: Software Development :: Libraries :: Python Modules
Classifier: Topic :: System :: Monitoring
Provides-Extra: code-format
Provides-Extra: code-lint
Provides-Extra: docs
Provides-Extra: keyvault
Provides-Extra: test
Requires-Dist: azure-keyvault (>=1.1,<2.0); extra == "keyvault"
Requires-Dist: black (>=19.3b0,<20.0); extra == "code-format"
Requires-Dist: blacken-docs (>=0.5.0,<0.6.0); extra == "code-format"
Requires-Dist: flake8 (>=3.7,<4.0); extra == "code-lint"
Requires-Dist: flake8-bandit (>=2.1,<3.0); extra == "code-lint"
Requires-Dist: flake8-blind-except (>=0.1.1,<0.2.0); extra == "code-lint"
Requires-Dist: flake8-bugbear (>=19.3,<20.0); extra == "code-lint"
Requires-Dist: flake8-builtins (>=1.4,<2.0); extra == "code-lint"
Requires-Dist: flake8-docstrings (>=1.3,<2.0); extra == "code-lint"
Requires-Dist: flake8-import-order (>=0.18.1,<0.19.0); extra == "code-lint"
Requires-Dist: flake8-logging-format (>=0.6.0,<0.7.0); extra == "code-lint"
Requires-Dist: pep8-naming (>=0.8.2,<0.9.0); extra == "code-lint"
Requires-Dist: pygments (>=2.4,<3.0); extra == "code-lint"
Requires-Dist: pytest (>=4.4.2,<5.0.0); extra == "test"
Requires-Dist: pytest-cov (>=2.7,<3.0); extra == "test"
Requires-Dist: pytest-dockerc (>=1.0,<2.0); extra == "test"
Requires-Dist: pytest-instafail (>=0.4.1,<0.5.0); extra == "test"
Requires-Dist: pytest-lazy-fixture (>=0.5.2,<0.6.0); extra == "test"
Requires-Dist: pytest-random-order (>=1.0,<2.0); extra == "test"
Requires-Dist: pytest-variables[yaml] (>=1.7,<2.0); extra == "test"
Requires-Dist: recommonmark (>=0.5.0,<0.6.0); extra == "docs"
Requires-Dist: selenium (>=3.141,<4.0)
Requires-Dist: sphinx (>=2.0,<3.0); extra == "docs"
Requires-Dist: sphinx_rtd_theme (>=0.4.3,<0.5.0); extra == "docs"
Project-URL: Repository, https://github.com/undp/SeleniumProbes
